README.md
setup.py
HieTaSumm/Files.py
HieTaSumm/Frame.py
HieTaSumm/Graph.py
HieTaSumm/Models.py
HieTaSumm/Summary.py
HieTaSumm/__init__.py
HieTaSumm/options.json
HieTaSumm.egg-info/PKG-INFO
HieTaSumm.egg-info/SOURCES.txt
HieTaSumm.egg-info/dependency_links.txt
HieTaSumm.egg-info/requires.txt
HieTaSumm.egg-info/top_level.txt